{
  "name": "Synexta CRM Core Plugin",
  "version": "1.9",
  "download_url": "https://github.com/ASMASHR/wp-plugin-crm-core/raw/main/synexta-crm-core.zip",
  "homepage": "https://synexta.fr/",
  "sections": {
    "description": "Gestion centralisée des dépenses, factures, utilisateurs et événements. Ce plugin CRM tout-en-un permet de suivre vos transactions, organiser vos événements, gérer vos contacts et collaborateurs, et conserver un historique complet des activités. Conçu pour optimiser la gestion de votre entreprise directement depuis WordPress.\n\nAjout d'une nouvelle fonctionnalité de mise à jour automatique."
  }
}
